metatrader5EasyT/__init__.py
metatrader5EasyT/initialization.py
metatrader5EasyT/rates.py
metatrader5EasyT/tick.py
metatrader5EasyT/timeframe.py
metatrader5EasyT/trade.py
tests/__init__.py
tests/conftest.py
tests/test_initialization.py
tests/test_rates.py
tests/test_tick.py
tests/test_trade.py
metatrader5EasyT-0.1.11.dist-info/LICENSE
metatrader5EasyT-0.1.11.dist-info/METADATA
metatrader5EasyT-0.1.11.dist-info/WHEEL
metatrader5EasyT-0.1.11.dist-info/top_level.txt
metatrader5EasyT-0.1.11.dist-info/RECORD
