Metadata-Version: 2.1
Name: metatrader5EasyT
Version: 0.1.11
Summary: UNKNOWN
Home-page: https://github.com/Joaopeuko/metatrader5EasyT
Author: Joao Paulo Euko
License: MIT
Keywords: metatrader5,algotrading,stock market
Platform: UNKNOWN
License-File: LICENSE
Requires-Dist: numpy
Requires-Dist: pytest
Requires-Dist: coverage
Requires-Dist: pytest-cov
Requires-Dist: MetaTrader5
Requires-Dist: abstractEasyT
Requires-Dist: supportLibEasyT
